README.rst
setup.cfg
setup.py
python_yaml_logger.egg-info/PKG-INFO
python_yaml_logger.egg-info/SOURCES.txt
python_yaml_logger.egg-info/dependency_links.txt
python_yaml_logger.egg-info/requires.txt
python_yaml_logger.egg-info/top_level.txt
yamlformatter/__init__.py
yamlformatter/__version__.py
yamlformatter/yamlformatter.py