Metadata-Version: 1.1
Name: python-yaml-logger
Version: 0.3.1
Summary: YAML formatter for the standard Python logging module
Home-page: http://github.com/OldhamMade/python-yaml-logger
Author: Phillip B Oldham
Author-email: phillip.oldham@gmail.com
License: MIT
Platform: UNKNOWN
Classifier: Development Status :: 4 - Beta
Classifier: Intended Audience :: Developers
Classifier: License :: OSI Approved :: MIT License
Classifier: Operating System :: OS Independent
Classifier: Programming Language :: Python
Classifier: Programming Language :: Python :: 2
Classifier: Topic :: System :: Logging
